<?xml version="1.0" encoding="UTF-8" standalone="no"?>
<Empleados>
    <Empleado>
        <Identificador>1</Identificador>
        <Apellido>Ramírez</Apellido>
        <Departamento>7</Departamento>
        <Salario>1000.0</Salario>
        <Cargo>Consultor</Cargo>
    </Empleado>
    <Empleado>
        <Identificador>2</Identificador>
        <Apellido>Chavez</Apellido>
        <Departamento>10</Departamento>
        <Salario>500.0</Salario>
        <Cargo>Administrador</Cargo>
    </Empleado>
    <Empleado>
        <Identificador>3</Identificador>
        <Apellido>Gascón</Apellido>
        <Departamento>21</Departamento>
        <Salario>600.0</Salario>
        <Cargo>Por Especificar</Cargo>
    </Empleado>
</Empleados>
